{
  "Keur Massar-Boeuf": {
    "date": "04/04/2025",
    "typeStock": "matin",
    "Point de Vente": "Keur Massar",
    "Produit": "Boeuf",
    "Nombre": "22",
    "PU": "3600",
    "Montant": "79200",
    "Commentaire": ""
  },
  "Keur Massar-Veau": {
    "date": "04/04/2025",
    "typeStock": "matin",
    "Point de Vente": "Keur Massar",
    "Produit": "Veau",
    "Nombre": "10",
    "PU": "3800",
    "Montant": "38000",
    "Commentaire": ""
  },
  "Keur Massar-Poulet": {
    "date": "04/04/2025",
    "typeStock": "matin",
    "Point de Vente": "Keur Massar",
    "Produit": "Poulet",
    "Nombre": "100",
    "PU": "3500",
    "Montant": "350000",
    "Commentaire": ""
  }
}